py_xlsx_textconv/__init__.py
py_xlsx_textconv/__main__.py
py_xlsx_textconv/convert.py
py_xlsx_textconv/output.py
py_xlsx_textconv/parse_macro.py
py_xlsx_textconv-0.0.6.dist-info/entry_points.txt
py_xlsx_textconv-0.0.6.dist-info/WHEEL
py_xlsx_textconv-0.0.6.dist-info/METADATA
py_xlsx_textconv-0.0.6.dist-info/licenses/LICENSE
py_xlsx_textconv-0.0.6.dist-info/RECORD
