Metadata-Version: 2.1
Name: py-xlsx-textconv
Version: 0.0.6
Summary: Git textconv tool for excel
Author-email: IIBUN Toshiyuki <toshiyuki.iibun@gmail.com>
Requires-Python: >=3.7
Classifier: Development Status :: 3 - Alpha
Classifier: License :: OSI Approved :: MIT License
Classifier: Operating System :: OS Independent
Classifier: Programming Language :: Python :: 3
Classifier: Programming Language :: Python :: 3.10
Classifier: Programming Language :: Python :: 3.7
Classifier: Programming Language :: Python :: 3.8
Classifier: Programming Language :: Python :: 3.9
Requires-Dist: oletools>=0.60.1
Requires-Dist: openpyxl==3.0.*
Project-URL: Repository, https://github.com/tiibun/py-xlsx-textconv
